{
  "db_name": "PostgreSQL",
  "query": "INSERT INTO fills\n               (fill_id, venue, venue_order_id, client_order_id, market_id,\n                side, action, price_cents, qty, fee_cents, is_maker, at,\n                producer, strategy)\n               VALUES ($1,$2,$3,$4,$5,$6,$7,$8,$9,$10,$11,$12,$13,$14)\n               ON CONFLICT (fill_id) DO NOTHING",
  "describe": {
    "columns": [],
    "parameters": {
      "Left": [
        "Text",
        "Text",
        "Text",
        "Text",
        "Text",
        "Text",
        "Text",
        "Int8",
        "Int8",
        "Int8",
        "Bool",
        "Text",
        "Text",
        "Text"
      ]
    },
    "nullable": []
  },
  "hash": "10579a0985511d924b6cca991c5ddf09e15c00e418af8c3dd784674e02996525"
}
